[
  {
    "id": 354,
    "operatorId": 354,
    "name": "Jazz Pakistan",
    "bundle": false,
    "data": false,
    "pin": false,
    "supportsLocalAmounts": true,
    "supportsGeographicalRechargePlans": false,
    "denominationType": "RANGE",
    "senderCurrencyCode": "PKR",
    "senderCurrencySymbol": "₨",
    "destinationCurrencyCode": "PKR",
    "destinationCurrencySymbol": "₨",
    "commission": 7.0,
    "internationalDiscount": 7.0,
    "localDiscount": 0.0,
    "mostPopularAmount": 877,
    "mostPopularLocalAmount": null,
    "minAmount": 110.0,
    "maxAmount": 5000,
    "localMinAmount": null,
    "localMaxAmount": null,
    "country": {
      "isoName": "PK",
      "name": "Pakistan"
    },
    "fx": {
      "rate": 0.76722,
      "currencyCode": "PKR"
    },
    "logoUrls": [
      "https://s3.amazonaws.com/rld-operator/49358cb6-1c0d-412b-aa55-5bee80370de0-size-3.png",
      "https://s3.amazonaws.com/rld-operator/49358cb6-1c0d-412b-aa55-5bee80370de0-size-1.png",
      "https://s3.amazonaws.com/rld-operator/49358cb6-1c0d-412b-aa55-5bee80370de0-size-2.png"
    ],
    "fixedAmounts": [],
    "fixedAmountsDescriptions": {},
    "localFixedAmounts": [],
    "localFixedAmountsDescriptions": {},
    "suggestedAmounts": [175, 877, 1755, 2633, 3511, 4389, 5267],
    "suggestedAmountsMap": {},
    "geographicalRechargePlans": [],
    "promotions": []
  },
  {
    "id": 353,
    "operatorId": 353,
    "name": "Telenor Pakistan",
    "bundle": false,
    "data": false,
    "pin": false,
    "supportsLocalAmounts": true,
    "supportsGeographicalRechargePlans": false,
    "denominationType": "RANGE",
    "senderCurrencyCode": "PKR",
    "senderCurrencySymbol": "₨",
    "destinationCurrencyCode": "PKR",
    "destinationCurrencySymbol": "₨",
    "commission": 7.0,
    "internationalDiscount": 7.0,
    "localDiscount": 0.0,
    "mostPopularAmount": 877,
    "mostPopularLocalAmount": null,
    "minAmount": 50.0,
    "maxAmount": 5000,
    "localMinAmount": null,
    "localMaxAmount": null,
    "country": {
      "isoName": "PK",
      "name": "Pakistan"
    },
    "fx": {
      "rate": 0.77822,
      "currencyCode": "PKR"
    },
    "logoUrls": [
      "https://s3.amazonaws.com/rld-operator/f4e48433-f54b-4821-9640-fb93e2d77a33-size-2.png",
      "https://s3.amazonaws.com/rld-operator/f4e48433-f54b-4821-9640-fb93e2d77a33-size-1.png",
      "https://s3.amazonaws.com/rld-operator/f4e48433-f54b-4821-9640-fb93e2d77a33-size-3.png"
    ],
    "fixedAmounts": [],
    "fixedAmountsDescriptions": {},
    "localFixedAmounts": [],
    "localFixedAmountsDescriptions": {},
    "suggestedAmounts": [175, 877, 1755, 2633, 3511, 4389, 5267],
    "suggestedAmountsMap": {},
    "geographicalRechargePlans": [],
    "promotions": []
  },
  {
    "id": 804,
    "operatorId": 804,
    "name": "Telenor Pakistan Bundles",
    "bundle": true,
    "data": false,
    "pin": false,
    "supportsLocalAmounts": true,
    "supportsGeographicalRechargePlans": false,
    "denominationType": "FIXED",
    "senderCurrencyCode": "PKR",
    "senderCurrencySymbol": "₨",
    "destinationCurrencyCode": "PKR",
    "destinationCurrencySymbol": "₨",
    "commission": 0.0,
    "internationalDiscount": 0.0,
    "localDiscount": 0.0,
    "mostPopularAmount": 800.0,
    "mostPopularLocalAmount": null,
    "minAmount": null,
    "maxAmount": null,
    "localMinAmount": null,
    "localMaxAmount": null,
    "country": {
      "isoName": "PK",
      "name": "Pakistan"
    },
    "fx": {
      "rate": 1,
      "currencyCode": "PKR"
    },
    "logoUrls": [
      "https://s3.amazonaws.com/rld-operator/f4e48433-f54b-4821-9640-fb93e2d77a33-size-2.png",
      "https://s3.amazonaws.com/rld-operator/f4e48433-f54b-4821-9640-fb93e2d77a33-size-1.png",
      "https://s3.amazonaws.com/rld-operator/f4e48433-f54b-4821-9640-fb93e2d77a33-size-3.png"
    ],
    "fixedAmounts": [150.0, 210.0, 400.0, 450.0, 600.0, 800.0],
    "fixedAmountsDescriptions": {
      "150.00": "Easycard 150",
      "210.00": "Easycard 4G Weekly Ultra-alternate channels",
      "400.00": "3G Monthly Starter 400",
      "450.00": "Easy Card 450 AC",
      "600.00": "Easy Card 600",
      "800.00": "Easy Card 800 AC"
    },
    "localFixedAmounts": [],
    "localFixedAmountsDescriptions": null,
    "suggestedAmounts": [],
    "suggestedAmountsMap": {},
    "geographicalRechargePlans": [],
    "promotions": []
  },
  {
    "id": 355,
    "operatorId": 355,
    "name": "Ufone Pakistan",
    "bundle": false,
    "data": false,
    "pin": false,
    "supportsLocalAmounts": true,
    "supportsGeographicalRechargePlans": false,
    "denominationType": "RANGE",
    "senderCurrencyCode": "PKR",
    "senderCurrencySymbol": "₨",
    "destinationCurrencyCode": "PKR",
    "destinationCurrencySymbol": "₨",
    "commission": 7.0,
    "internationalDiscount": 7.0,
    "localDiscount": 0.0,
    "mostPopularAmount": 877,
    "mostPopularLocalAmount": null,
    "minAmount": 50.0,
    "maxAmount": 5000,
    "localMinAmount": null,
    "localMaxAmount": null,
    "country": {
      "isoName": "PK",
      "name": "Pakistan"
    },
    "fx": {
      "rate": 0.77822,
      "currencyCode": "PKR"
    },
    "logoUrls": [
      "https://s3.amazonaws.com/rld-operator/0938f681-a20f-485b-ab05-9b3fce7e888a-size-3.png",
      "https://s3.amazonaws.com/rld-operator/0938f681-a20f-485b-ab05-9b3fce7e888a-size-2.png",
      "https://s3.amazonaws.com/rld-operator/0938f681-a20f-485b-ab05-9b3fce7e888a-size-1.png"
    ],
    "fixedAmounts": [],
    "fixedAmountsDescriptions": {},
    "localFixedAmounts": [],
    "localFixedAmountsDescriptions": {},
    "suggestedAmounts": [175, 877, 1755, 2633, 3511, 4389, 5267],
    "suggestedAmountsMap": {},
    "geographicalRechargePlans": [],
    "promotions": []
  },
  {
    "id": 351,
    "operatorId": 351,
    "name": "Warid Pakistan",
    "bundle": false,
    "data": false,
    "pin": false,
    "supportsLocalAmounts": true,
    "supportsGeographicalRechargePlans": false,
    "denominationType": "RANGE",
    "senderCurrencyCode": "PKR",
    "senderCurrencySymbol": "₨",
    "destinationCurrencyCode": "PKR",
    "destinationCurrencySymbol": "₨",
    "commission": 7.0,
    "internationalDiscount": 7.0,
    "localDiscount": 0.0,
    "mostPopularAmount": 877,
    "mostPopularLocalAmount": null,
    "minAmount": 110.0,
    "maxAmount": 5000,
    "localMinAmount": null,
    "localMaxAmount": null,
    "country": {
      "isoName": "PK",
      "name": "Pakistan"
    },
    "fx": {
      "rate": 0.77822,
      "currencyCode": "PKR"
    },
    "logoUrls": [
      "https://s3.amazonaws.com/rld-operator/bca92b80-ff68-46bb-98c2-83bc21d61619-size-3.png",
      "https://s3.amazonaws.com/rld-operator/bca92b80-ff68-46bb-98c2-83bc21d61619-size-1.png",
      "https://s3.amazonaws.com/rld-operator/bca92b80-ff68-46bb-98c2-83bc21d61619-size-2.png"
    ],
    "fixedAmounts": [],
    "fixedAmountsDescriptions": {},
    "localFixedAmounts": [],
    "localFixedAmountsDescriptions": {},
    "suggestedAmounts": [175, 877, 1755, 2633, 3511, 4389, 5267],
    "suggestedAmountsMap": {},
    "geographicalRechargePlans": [],
    "promotions": []
  },
  {
    "id": 352,
    "operatorId": 352,
    "name": "Zong Pakistan",
    "bundle": false,
    "data": false,
    "pin": false,
    "supportsLocalAmounts": true,
    "supportsGeographicalRechargePlans": false,
    "denominationType": "RANGE",
    "senderCurrencyCode": "PKR",
    "senderCurrencySymbol": "₨",
    "destinationCurrencyCode": "PKR",
    "destinationCurrencySymbol": "₨",
    "commission": 7.0,
    "internationalDiscount": 7.0,
    "localDiscount": 0.0,
    "mostPopularAmount": 1755,
    "mostPopularLocalAmount": null,
    "minAmount": 50.0,
    "maxAmount": 20000,
    "localMinAmount": null,
    "localMaxAmount": null,
    "country": {
      "isoName": "PK",
      "name": "Pakistan"
    },
    "fx": {
      "rate": 0.7752,
      "currencyCode": "PKR"
    },
    "logoUrls": [
      "https://s3.amazonaws.com/rld-operator/b4765265-9038-495a-aeb7-b3403011d510-size-1.png",
      "https://s3.amazonaws.com/rld-operator/b4765265-9038-495a-aeb7-b3403011d510-size-2.png",
      "https://s3.amazonaws.com/rld-operator/b4765265-9038-495a-aeb7-b3403011d510-size-3.png"
    ],
    "fixedAmounts": [],
    "fixedAmountsDescriptions": {},
    "localFixedAmounts": [],
    "localFixedAmountsDescriptions": {},
    "suggestedAmounts": [
      175, 877, 1755, 2633, 3511, 4389, 5267, 6145, 7023, 7901, 8779, 9656,
      10534, 11412, 12290, 13168, 14046, 14924, 15802, 16680, 17558, 18436,
      19313, 20191, 21069, 21947, 22825, 23703, 24581, 25459, 26337, 27215,
      28093, 28970, 29848, 30726, 31604, 32482, 33360, 34238, 35116, 35994,
      36872, 37750, 38627, 39505, 40383, 41261, 42139, 43017, 43895, 44773,
      45651, 46529, 47407, 48284, 49162, 50040, 50918, 51796, 52674
    ],
    "suggestedAmountsMap": {},
    "geographicalRechargePlans": [],
    "promotions": []
  },
  {
    "id": 787,
    "operatorId": 787,
    "name": "Zong Pakistan Bundles",
    "bundle": true,
    "data": false,
    "pin": false,
    "supportsLocalAmounts": true,
    "supportsGeographicalRechargePlans": false,
    "denominationType": "FIXED",
    "senderCurrencyCode": "PKR",
    "senderCurrencySymbol": "₨",
    "destinationCurrencyCode": "PKR",
    "destinationCurrencySymbol": "₨",
    "commission": 0.0,
    "internationalDiscount": 0.0,
    "localDiscount": 0.0,
    "mostPopularAmount": 2629.0,
    "mostPopularLocalAmount": null,
    "minAmount": null,
    "maxAmount": null,
    "localMinAmount": null,
    "localMaxAmount": null,
    "country": {
      "isoName": "PK",
      "name": "Pakistan"
    },
    "fx": {
      "rate": 1,
      "currencyCode": "PKR"
    },
    "logoUrls": [
      "https://s3.amazonaws.com/rld-operator/b4765265-9038-495a-aeb7-b3403011d510-size-1.png",
      "https://s3.amazonaws.com/rld-operator/b4765265-9038-495a-aeb7-b3403011d510-size-2.png",
      "https://s3.amazonaws.com/rld-operator/b4765265-9038-495a-aeb7-b3403011d510-size-3.png"
    ],
    "fixedAmounts": [
      185.0, 200.0, 270.0, 340.0, 675.0, 850.0, 1270.0, 1550.0, 2629.0
    ],
    "fixedAmountsDescriptions": {
      "185.00": "Super Weekly Offer 3GB Flat + 25 All Net Min (7 days)    Re-Subscription is Allowed   \tNormal Prepaid Customer",
      "200.00": "AIO Weekly 3GB, 5000 Onnet min, 40 Offnet min and 5000 SMS (7 days)    Customer has to Un-sub   \tNormal Prepaid Customer",
      "270.00": "Haftawar Load Offer 9GB Flat, 80 Off-Net Mins, 5000 On-Net Mins + SMS  (7 days)    Customer has to Un-sub   \tNormal Prepaid Customer",
      "340.00": "Super Weekly Premium 30 GB Flat, 100 All Net Mins, 5,000 On-net Mins + SMS (7 days)    Re-Subscription is Allowed   \tNormal Prepaid Customer",
      "675.00": "All-In-One Monthly/ ZONG Super Card 5000 ON Net & 180 Off Net Minutes, 5000 SMS, 6GB Flat (30 days)    Customer has to Un-sub   \tNormal Prepaid Customer",
      "850.00": "Supreme Offer 5,000 ON Net & 300 Off Net Minutes, 5,000 SMS, 12GB Flat (30 days)    Customer has to Un-sub   \tNormal Prepaid Customer",
      "1270.00": "Monthly Super 30GB (including 6GB Youtube+4GB Whatsapp), 5000 On-net & SMS, 300 Other network  (30 days)    Customer has to Un-sub   \tNormal Prepaid Customer",
      "1550.00": "Supreme Plus Offer 10,000 ON Net & 600 Off Net Minutes, 10,000 SMS, 30GB Flat (30 days)    Re-Subscription is Allowed   \tNormal Prepaid Customer",
      "2629.00": "KSA Offer 2000 KSA Prepaid IR bundle 60Mins , 60 SMS, 512 MB Data (90 days)    Customer has to Un-sub   \tNormal Prepaid Customer"
    },
    "localFixedAmounts": [],
    "localFixedAmountsDescriptions": null,
    "suggestedAmounts": [],
    "suggestedAmountsMap": {},
    "geographicalRechargePlans": [],
    "promotions": []
  },
  {
    "id": 1010,
    "operatorId": 1010,
    "name": "Zong Pakistan Data",
    "bundle": false,
    "data": true,
    "pin": false,
    "supportsLocalAmounts": true,
    "supportsGeographicalRechargePlans": false,
    "denominationType": "FIXED",
    "senderCurrencyCode": "PKR",
    "senderCurrencySymbol": "₨",
    "destinationCurrencyCode": "PKR",
    "destinationCurrencySymbol": "₨",
    "commission": 0.0,
    "internationalDiscount": 0.0,
    "localDiscount": 0.0,
    "mostPopularAmount": 12000.0,
    "mostPopularLocalAmount": null,
    "minAmount": null,
    "maxAmount": null,
    "localMinAmount": null,
    "localMaxAmount": null,
    "country": {
      "isoName": "PK",
      "name": "Pakistan"
    },
    "fx": {
      "rate": 1,
      "currencyCode": "PKR"
    },
    "logoUrls": [
      "https://s3.amazonaws.com/rld-operator/b4765265-9038-495a-aeb7-b3403011d510-size-1.png",
      "https://s3.amazonaws.com/rld-operator/b4765265-9038-495a-aeb7-b3403011d510-size-2.png",
      "https://s3.amazonaws.com/rld-operator/b4765265-9038-495a-aeb7-b3403011d510-size-3.png"
    ],
    "fixedAmounts": [
      59.0, 98.0, 108.0, 132.0, 240.0, 290.0, 300.0, 550.0, 899.0, 2000.0,
      2500.0, 3150.0, 12000.0
    ],
    "fixedAmountsDescriptions": {
      "59.00": "Whatsapp Offer 5GB WhatsApp Data (30 days)    Customer has to Un-sub   \tNormal Prepaid Customer",
      "98.00": "WhatsApp Plus Offer 4GB WhatsApp Data + 20 off-net+ 200 on-net  (30 days)    Customer has to Un-sub   \tNormal Prepaid Customer",
      "108.00": "Monthly Facebook 6 GB (30 days)    Customer has to Un-sub   \tNormal Prepaid Customer",
      "132.00": "Weekly Youtube 8 GB (7 days)    Re-Subscription is Allowed   \tNormal Prepaid Customer",
      "240.00": "Super Weekly Plus 7 GB + 1GB Whatsapp (7 days)    Re-Subscription is Allowed   \tNormal Prepaid Customer",
      "290.00": "Monthly Premium 5 GB 5 GB (300 days)    Customer has to Un-sub   \tNormal Prepaid Customer",
      "300.00": "Super Weekly Max 30 GB [16GB + 14GB Youtube] (7 days)    Customer has to Un-sub   \tNormal Prepaid Customer",
      "550.00": "Monthly Premium 15 GB/ Monthly Super Plus 10GB +10GB  (1AM till 9am ) (30 days)    Customer has to Un-sub   \tNormal Prepaid Customer",
      "899.00": "Monthly Premium 40 GB/ Monthly Super Max 20GB+20GB GNO (01 AM- 09 AM) (30 days)    Customer has to Un-sub   \tNormal Prepaid Customer",
      "2000.00": "Prepaid MBB Monthly 65GB 65 GB (30 days)    Re-Subscription is Allowed   \tNormal Prepaid Customer",
      "2500.00": "Prepaid MBB Monthly 80+80 GB (4AM to 4PM) 160 GB (Inc. 80GB 4:00 AM to 4:00 PM) (30 days)    Re-Subscription is Allowed   \tNormal Prepaid Customer",
      "3150.00": "Prepaid MBB Monthly 200 GB (Inc. 100 GB - 4AM to 4PM) 100 GB + 100 GB( 4AM to 4PM) (30 days)    Re-Subscription is Allowed   \tNormal Prepaid Customer",
      "12000.00": "Prepaid MBB 6 Months Bundle 105GB/Month 75 GB + 30 GB( 4AM to 4PM) (180 days)    Re-Subscription is Allowed   \tNormal Prepaid Customer"
    },
    "localFixedAmounts": [],
    "localFixedAmountsDescriptions": null,
    "suggestedAmounts": [],
    "suggestedAmountsMap": {},
    "geographicalRechargePlans": [],
    "promotions": []
  }
]
